pytemperature/__init__.py
pytemperature-1.1.dist-info/LICENSE
pytemperature-1.1.dist-info/METADATA
pytemperature-1.1.dist-info/WHEEL
pytemperature-1.1.dist-info/top_level.txt
pytemperature-1.1.dist-info/RECORD
