Metadata-Version: 2.1
Name: pytemperature
Version: 1.1
Summary: Scale of temperature
Home-page: https://github.com/wannaphong/pytemperature
Author: Wannaphong Phatthiyaphaibun
Author-email: wannaphong@yahoo.com
License: MIT
Keywords: temperature science
Platform: UNKNOWN
Classifier: Development Status :: 5 - Production/Stable
Classifier: Intended Audience :: Developers
Classifier: Natural Language :: English
Classifier: License :: OSI Approved :: MIT License
Classifier: Operating System :: OS Independent
Classifier: Programming Language :: Python
Classifier: Programming Language :: Python :: 3
Classifier: Topic :: Scientific/Engineering
Requires-Python: >=3.6
License-File: LICENSE
